Metadata-Version: 2.1
Name: core-module-raw-xml-app
Version: 2.19.0
Summary: Raw xml module for the parser core project
Home-page: https://github.com/usnistgov/core_module_raw_xml_app
Author: NIST IT Lab
Author-email: itl_inquiries@nist.gov
License-File: LICENSE.md
